MANIFEST.in
README.rst
requirements.txt
setup.py
coscmd/__init__.py
coscmd/cos_auth.py
coscmd/cos_client.py
coscmd/cos_cmd.py
coscmd/cos_comm.py
coscmd/cos_global.py
coscmd/cos_sync.py
coscmd/cos_threadpool.py
coscmd/test.py
coscmd/l5/__init__.py
coscmd/l5/l5sys.so
l_coscmd.egg-info/PKG-INFO
l_coscmd.egg-info/SOURCES.txt
l_coscmd.egg-info/dependency_links.txt
l_coscmd.egg-info/entry_points.txt
l_coscmd.egg-info/requires.txt
l_coscmd.egg-info/top_level.txt